<bpy>
  <Theme>
    <user_interface>
      <ThemeUserInterface
        menu_shadow_fac="0.01"
        menu_shadow_width="0"
        icon_alpha="1"
        icon_saturation="0.5"
        widget_emboss="#00000000"
        editor_outline="#000000"
        widget_text_cursor="#38738c"
        panel_roundness="0.5"
        transparent_checker_primary="#252525"
        transparent_checker_secondary="#181818"
        transparent_checker_size="8"
        axis_x="#ff2647"
        axis_y="#91e600"
        axis_z="#268fff"
        gizmo_hi="#ffffff"
        gizmo_primary="#f5f14d"
        gizmo_secondary="#63ffff"
        gizmo_view_align="#ffffff"
        gizmo_a="#4da84d"
        gizmo_b="#a33535"
        icon_scene="#ccccccff"
        icon_collection="#eeeeeeff"
        icon_object="#cc793dff"
        icon_object_data="#00bf9cff"
        icon_modifier="#4580d9ff"
        icon_shading="#bf4c4cff"
        icon_folder="#4c9dbfff"
        icon_border_intensity="0"
        >
        <wcol_regular>
          <ThemeWidgetColors
            outline="#3d3d3d00"
            inner="#252525ff"
            inner_sel="#38738cff"
            item="#1d1d1d80"
            text="#e6e6e6"
            text_sel="#ffffff"
            show_shaded="FALSE"
            shadetop="0"
            shadedown="0"
            roundness="0.5"
            >
          </ThemeWidgetColors>
        </wcol_regular>
        <wcol_tool>
          <ThemeWidgetColors
            outline="#10101000"
            inner="#252525ff"
            inner_sel="#38738cff"
            item="#ffffffff"
            text="#e6e6e6"
            text_sel="#ffffff"
            show_shaded="FALSE"
            shadetop="0"
            shadedown="0"
            roundness="0.5"
            >
          </ThemeWidgetColors>
        </wcol_tool>
        <wcol_toolbar_item>
          <ThemeWidgetColors
            outline="#10101000"
            inner="#151515ff"
            inner_sel="#38738cff"
            item="#ffffffb3"
            text="#e6e6e6"
            text_sel="#ffffff"
            show_shaded="FALSE"
            shadetop="0"
            shadedown="0"
            roundness="0.5"
            >
          </ThemeWidgetColors>
        </wcol_toolbar_item>
        <wcol_radio>
          <ThemeWidgetColors
            outline="#3d3d3d00"
            inner="#252525ff"
            inner_sel="#38738cff"
            item="#252525ff"
            text="#e6e6e6"
            text_sel="#ffffff"
            show_shaded="FALSE"
            shadetop="0"
            shadedown="0"
            roundness="0.5"
            >
          </ThemeWidgetColors>
        </wcol_radio>
        <wcol_text>
          <ThemeWidgetColors
            outline="#3d3d3d00"
            inner="#101010ff"
            inner_sel="#101010ff"
            item="#ffffff33"
            text="#e6e6e6"
            text_sel="#ffffff"
            show_shaded="FALSE"
            shadetop="0"
            shadedown="0"
            roundness="0.5"
            >
          </ThemeWidgetColors>
        </wcol_text>
        <wcol_option>
          <ThemeWidgetColors
            outline="#3d3d3d00"
            inner="#303030ff"
            inner_sel="#38738cff"
            item="#ffffffff"
            text="#e6e6e6"
            text_sel="#ffffff"
            show_shaded="FALSE"
            shadetop="0"
            shadedown="0"
            roundness="0.5"
            >
          </ThemeWidgetColors>
        </wcol_option>
        <wcol_toggle>
          <ThemeWidgetColors
            outline="#3d3d3d00"
            inner="#252525ff"
            inner_sel="#38738cff"
            item="#252525ff"
            text="#e6e6e6"
            text_sel="#ffffff"
            show_shaded="FALSE"
            shadetop="0"
            shadedown="0"
            roundness="0.5"
            >
          </ThemeWidgetColors>
        </wcol_toggle>
        <wcol_num>
          <ThemeWidgetColors
            outline="#30303000"
            inner="#252525ff"
            inner_sel="#222222ff"
            item="#38738cff"
            text="#e6e6e6"
            text_sel="#ffffff"
            show_shaded="FALSE"
            shadetop="0"
            shadedown="0"
            roundness="0.5"
            >
          </ThemeWidgetColors>
        </wcol_num>
        <wcol_numslider>
          <ThemeWidgetColors
            outline="#10101000"
            inner="#101010ff"
            inner_sel="#222222ff"
            item="#38738cff"
            text="#e6e6e6"
            text_sel="#ffffff"
            show_shaded="FALSE"
            shadetop="0"
            shadedown="0"
            roundness="0.5"
            >
          </ThemeWidgetColors>
        </wcol_numslider>
        <wcol_box>
          <ThemeWidgetColors
            outline="#3d3d3d00"
            inner="#101010ff"
            inner_sel="#545454ff"
            item="#191919ff"
            text="#e6e6e6"
            text_sel="#ffffff"
            show_shaded="FALSE"
            shadetop="0"
            shadedown="0"
            roundness="0.5"
            >
          </ThemeWidgetColors>
        </wcol_box>
        <wcol_menu>
          <ThemeWidgetColors
            outline="#3d3d3d00"
            inner="#252525ff"
            inner_sel="#38738cff"
            item="#d9d9d9ff"
            text="#e6e6e6"
            text_sel="#ffffff"
            show_shaded="FALSE"
            shadetop="0"
            shadedown="0"
            roundness="0.5"
            >
          </ThemeWidgetColors>
        </wcol_menu>
        <wcol_pulldown>
          <ThemeWidgetColors
            outline="#3d3d3d00"
            inner="#20202000"
            inner_sel="#ffffff1a"
            item="#ffffff8f"
            text="#d9d9d9"
            text_sel="#ffffff"
            show_shaded="FALSE"
            shadetop="0"
            shadedown="0"
            roundness="0.5"
            >
          </ThemeWidgetColors>
        </wcol_pulldown>
        <wcol_menu_back>
          <ThemeWidgetColors
            outline="#24242400"
            inner="#151515ff"
            inner_sel="#38738cff"
            item="#d9d9d9ff"
            text="#999999"
            text_sel="#ffffff"
            show_shaded="FALSE"
            shadetop="0"
            shadedown="0"
            roundness="0.7"
            >
          </ThemeWidgetColors>
        </wcol_menu_back>
        <wcol_pie_menu>
          <ThemeWidgetColors
            outline="#24242400"
            inner="#151515ff"
            inner_sel="#38738cff"
            item="#333333ff"
            text="#d9d9d9"
            text_sel="#ffffff"
            show_shaded="FALSE"
            shadetop="0"
            shadedown="0"
            roundness="0.7"
            >
          </ThemeWidgetColors>
        </wcol_pie_menu>
        <wcol_tooltip>
          <ThemeWidgetColors
            outline="#10101000"
            inner="#151515ff"
            inner_sel="#38738cff"
            item="#d9d9d9ff"
            text="#d9d9d9"
            text_sel="#ffffff"
            show_shaded="FALSE"
            shadetop="0"
            shadedown="0"
            roundness="0.5"
            >
          </ThemeWidgetColors>
        </wcol_tooltip>
        <wcol_menu_item>
          <ThemeWidgetColors
            outline="#22222200"
            inner="#18181800"
            inner_sel="#38738cff"
            item="#ffffff80"
            text="#dddddd"
            text_sel="#ffffff"
            show_shaded="FALSE"
            shadetop="0"
            shadedown="0"
            roundness="0.5"
            >
          </ThemeWidgetColors>
        </wcol_menu_item>
        <wcol_scroll>
          <ThemeWidgetColors
            outline="#25252500"
            inner="#22222200"
            inner_sel="#ffffffff"
            item="#303030cc"
            text="#e6e6e6"
            text_sel="#ffffff"
            show_shaded="FALSE"
            shadetop="0"
            shadedown="0"
            roundness="1"
            >
          </ThemeWidgetColors>
        </wcol_scroll>
        <wcol_progress>
          <ThemeWidgetColors
            outline="#3d3d3d00"
            inner="#151515ff"
            inner_sel="#38738cff"
            item="#38738cff"
            text="#e6e6e6"
            text_sel="#ffffff"
            show_shaded="FALSE"
            shadetop="0"
            shadedown="0"
            roundness="0.5"
            >
          </ThemeWidgetColors>
        </wcol_progress>
        <wcol_list_item>
          <ThemeWidgetColors
            outline="#2d2d2d00"
            inner="#ffffff00"
            inner_sel="#38738cff"
            item="#ffffff33"
            text="#cccccc"
            text_sel="#ffffff"
            show_shaded="FALSE"
            shadetop="0"
            shadedown="0"
            roundness="0.5"
            >
          </ThemeWidgetColors>
        </wcol_list_item>
        <wcol_state>
          <ThemeWidgetStateColors
            inner_anim="#53992e"
            inner_anim_sel="#38a600"
            inner_key="#b3ae36"
            inner_key_sel="#b29700"
            inner_driven="#9000cc"
            inner_driven_sel="#9900e6"
            inner_overridden="#00c3c3"
            inner_overridden_sel="#118f8f"
            inner_changed="#cc7529"
            inner_changed_sel="#d26400"
            blend="0.5"
            >
          </ThemeWidgetStateColors>
        </wcol_state>
        <wcol_tab>
          <ThemeWidgetColors
            outline="#15151500"
            inner="#09090900"
            inner_sel="#151515ff"
            item="#181818ff"
            text="#989898"
            text_sel="#ffffff"
            show_shaded="FALSE"
            shadetop="0"
            shadedown="0"
            roundness="0.4"
            >
          </ThemeWidgetColors>
        </wcol_tab>
      </ThemeUserInterface>
    </user_interface>
    <view_3d>
      <ThemeView3D
        grid="#44444480"
        clipping_border_3d="#3f3f3fff"
        wire="#000000"
        wire_edit="#000000"
        edge_width="2"
        gp_vertex="#000000"
        gp_vertex_select="#ff8500"
        gp_vertex_size="3"
        text_grease_pencil="#7a9b14"
        object_selected="#ed5700"
        object_active="#ffa028"
        text_keyframe="#ddd700"
        camera="#000000"
        empty="#000000"
        light="#00000050"
        speaker="#000000"
        vertex="#000000"
        vertex_select="#ff7a00"
        vertex_size="3"
        vertex_bevel="#00a5ff"
        vertex_unreferenced="#000000"
        edge_select="#ff9900"
        edge_mode_select="#ffd800"
        edge_seam="#db2512"
        edge_sharp="#00ffff"
        edge_crease="#cc0099"
        edge_bevel="#00a5ff"
        edge_facesel="#4b4b4b"
        freestyle_edge_mark="#7fff7f"
        face="#ffffff02"
        face_select="#ffa30033"
        face_mode_select="#ffb70033"
        face_dot="#ff8a00"
        facedot_size="3"
        freestyle_face_mark="#7fff7f4d"
        face_retopology="#50c8ff0f"
        face_back="#ff0000b3"
        face_front="#0000ffb3"
        nurb_uline="#909000"
        nurb_vline="#803060"
        nurb_sel_uline="#f0ff40"
        nurb_sel_vline="#f090a0"
        act_spline="#db2512"
        handle_free="#000000"
        handle_auto="#909000"
        handle_vect="#409030"
        handle_sel_vect="#40c030"
        handle_align="#803060"
        handle_sel_free="#000000"
        handle_sel_auto="#f0ff40"
        handle_sel_align="#f090a0"
        lastsel_point="#ffffff"
        extra_edge_len="#150806"
        extra_edge_angle="#4d4d00"
        extra_face_angle="#0000cc"
        extra_face_area="#004d00"
        editmesh_active="#ffffff33"
        normal="#22dddd"
        vertex_normal="#2361dd"
        split_normal="#dd23dd"
        bone_pose="#50c8ff"
        bone_pose_active="#8cffff"
        bone_solid="#b2b2b2"
        bone_locked_weight="#ff000080"
        bundle_solid="#c8c8c8"
        camera_path="#000000"
        camera_passepartout="#000000"
        skin_root="#b44d4d"
        view_overlay="#000000"
        transform="#ffffff"
        frame_current="#38738c"
        paint_curve_handle="#7fff7f7f"
        paint_curve_pivot="#ff7f7f7f"
        outline_width="3"
        object_origin_size="6"
        >
        <space>
          <ThemeSpaceGradient
            title="#eeeeee"
            text="#e6e6e6"
            text_hi="#ffffff"
            header="#181818cc"
            header_text="#eeeeee"
            header_text_hi="#ffffff"
            button="#15151500"
            button_title="#ffffff"
            button_text="#cccccc"
            button_text_hi="#ffffff"
            navigation_bar="#151515ff"
            execution_buts="#151515ff"
            tab_active="#151515"
            tab_inactive="#090909"
            tab_back="#090909ff"
            tab_outline="#10101000"
            >
            <gradients>
              <ThemeGradientColors
                background_type="SINGLE_COLOR"
                high_gradient="#151515"
                gradient="#1c1c1c"
                >
              </ThemeGradientColors>
            </gradients>
            <panelcolors>
              <ThemePanelColors
                header="#181818ff"
                back="#181818ff"
                sub_back="#00000000"
                >
              </ThemePanelColors>
            </panelcolors>
          </ThemeSpaceGradient>
        </space>
        <asset_shelf>
          <ThemeAssetShelf
            header_back="#1d1d1dff"
            back="#303030ff"
            >
          </ThemeAssetShelf>
        </asset_shelf>
      </ThemeView3D>
    </view_3d>
    <graph_editor>
      <ThemeGraphEditor
        grid="#222222"
        frame_current="#38738c"
        time_scrub_background="#161616ff"
        time_marker_line="#ffffff4d"
        time_marker_line_selected="#ffffffb3"
        window_sliders="#969696"
        channels_region="#121212"
        dopesheet_channel="#194e80"
        dopesheet_subchannel="#0f2c4d"
        channel_group="#1a332d"
        active_channels_group="#216d5b"
        preview_range="#a14d0066"
        vertex="#000000"
        vertex_select="#ff8500"
        vertex_active="#ffffff"
        vertex_size="6"
        vertex_bevel="#000000"
        vertex_unreferenced="#000000"
        handle_free="#000000"
        handle_auto="#909000"
        handle_vect="#409030"
        handle_sel_vect="#40c030"
        handle_align="#803060"
        handle_sel_free="#000000"
        handle_sel_auto="#f0ff40"
        handle_sel_align="#f090a0"
        handle_auto_clamped="#994030"
        handle_sel_auto_clamped="#f0af90"
        lastsel_point="#ffffff"
        handle_vertex="#000000"
        handle_vertex_select="#ff8500"
        handle_vertex_size="5"
        >
        <space>
          <ThemeSpaceGeneric
            back="#151515"
            title="#ffffff"
            text="#a6a6a6"
            text_hi="#ffffff"
            header="#181818ff"
            header_text="#eeeeee"
            header_text_hi="#ffffff"
            button="#151515ff"
            button_title="#ffffff"
            button_text="#cccccc"
            button_text_hi="#ffffff"
            navigation_bar="#151515ff"
            execution_buts="#151515ff"
            tab_active="#151515"
            tab_inactive="#090909"
            tab_back="#090909ff"
            tab_outline="#10101000"
            >
            <panelcolors>
              <ThemePanelColors
                header="#181818ff"
                back="#181818ff"
                sub_back="#00000000"
                >
              </ThemePanelColors>
            </panelcolors>
          </ThemeSpaceGeneric>
        </space>
        <space_list>
          <ThemeSpaceListGeneric
            list="#1d1d1d"
            list_title="#ffffff"
            list_text="#b8b8b8"
            list_text_hi="#ffaf23"
            >
          </ThemeSpaceListGeneric>
        </space_list>
      </ThemeGraphEditor>
    </graph_editor>
    <file_browser>
      <ThemeFileBrowser
        selected_file="#2e5e72"
        row_alternate="#ffffff04"
        >
        <space>
          <ThemeSpaceGeneric
            back="#151515"
            title="#ffffff"
            text="#e6e6e6"
            text_hi="#ffffff"
            header="#181818ff"
            header_text="#eeeeee"
            header_text_hi="#ffffff"
            button="#151515ff"
            button_title="#ffffff"
            button_text="#cccccc"
            button_text_hi="#ffffff"
            navigation_bar="#151515ff"
            execution_buts="#151515ff"
            tab_active="#151515"
            tab_inactive="#090909"
            tab_back="#090909ff"
            tab_outline="#10101000"
            >
            <panelcolors>
              <ThemePanelColors
                header="#181818ff"
                back="#181818ff"
                sub_back="#00000000"
                >
              </ThemePanelColors>
            </panelcolors>
          </ThemeSpaceGeneric>
        </space>
      </ThemeFileBrowser>
    </file_browser>
    <nla_editor>
      <ThemeNLAEditor
        grid="#222222"
        view_sliders="#969696"
        dopesheet_channel="#0f2c4d"
        dopesheet_subchannel="#7d98b3"
        nla_track="#303030"
        active_action="#99541366"
        active_action_unset="#4d3b174d"
        preview_range="#a14d0066"
        strips="#0d0d0d"
        strips_selected="#ff8c00"
        transition_strips="#1c2630"
        transition_strips_selected="#2e75db"
        meta_strips="#332642"
        meta_strips_selected="#692196"
        sound_strips="#2b3d3d"
        sound_strips_selected="#1f7a7a"
        tweak="#4df31a"
        tweak_duplicate="#d90000"
        keyframe_border="#000000ff"
        keyframe_border_selected="#000000ff"
        frame_current="#4772b3"
        time_scrub_background="#161616ff"
        time_marker_line="#ffffff4d"
        time_marker_line_selected="#ffffffb3"
        >
        <space>
          <ThemeSpaceGeneric
            back="#151515"
            title="#ffffff"
            text="#a6a6a6"
            text_hi="#ffffff"
            header="#181818ff"
            header_text="#eeeeee"
            header_text_hi="#ffffff"
            button="#1d1d1dff"
            button_title="#ffffff"
            button_text="#cccccc"
            button_text_hi="#ffffff"
            navigation_bar="#151515ff"
            execution_buts="#151515ff"
            tab_active="#151515"
            tab_inactive="#090909"
            tab_back="#090909ff"
            tab_outline="#10101000"
            >
            <panelcolors>
              <ThemePanelColors
                header="#181818ff"
                back="#181818ff"
                sub_back="#00000000"
                >
              </ThemePanelColors>
            </panelcolors>
          </ThemeSpaceGeneric>
        </space>
        <space_list>
          <ThemeSpaceListGeneric
            list="#1d1d1d"
            list_title="#ffffff"
            list_text="#b8b8b8"
            list_text_hi="#ffaf23"
            >
          </ThemeSpaceListGeneric>
        </space_list>
      </ThemeNLAEditor>
    </nla_editor>
    <dopesheet_editor>
      <ThemeDopeSheet
        grid="#555555"
        frame_current="#38738c"
        time_scrub_background="#1d1d1dff"
        time_marker_line="#ffffff4d"
        time_marker_line_selected="#ffffffb3"
        value_sliders="#000000"
        view_sliders="#c0c0c0"
        dopesheet_channel="#194e8080"
        dopesheet_subchannel="#0f2c4d80"
        channels="#1d1d1d99"
        channels_selected="#60c04044"
        channel_group="#0d26204f"
        active_channels_group="#216d5b67"
        long_key="#ffffff1f"
        long_key_selected="#ff8c0099"
        keyframe="#dddddd"
        keyframe_selected="#e67d39"
        keyframe_extreme="#e8b3cc"
        keyframe_extreme_selected="#f28080"
        keyframe_breakdown="#b3dbe8"
        keyframe_breakdown_selected="#54bfed"
        keyframe_jitter="#94e575"
        keyframe_jitter_selected="#61c042"
        keyframe_movehold="#808080"
        keyframe_movehold_selected="#ffaf23"
        keyframe_generated="#585858"
        keyframe_generated_selected="#a28962"
        keyframe_border="#000000ff"
        keyframe_border_selected="#000000ff"
        keyframe_scale_factor="1"
        summary="#4d1b1b66"
        preview_range="#a14d0066"
        interpolation_line="#94e575cc"
        simulated_frames="#721e65ff"
        >
        <space>
          <ThemeSpaceGeneric
            back="#151515"
            title="#eeeeee"
            text="#a6a6a6"
            text_hi="#ffffff"
            header="#181818ff"
            header_text="#eeeeee"
            header_text_hi="#ffffff"
            button="#151515ff"
            button_title="#ffffff"
            button_text="#cccccc"
            button_text_hi="#ffffff"
            navigation_bar="#151515ff"
            execution_buts="#151515ff"
            tab_active="#151515"
            tab_inactive="#090909"
            tab_back="#090909ff"
            tab_outline="#10101000"
            >
            <panelcolors>
              <ThemePanelColors
                header="#181818ff"
                back="#181818ff"
                sub_back="#00000000"
                >
              </ThemePanelColors>
            </panelcolors>
          </ThemeSpaceGeneric>
        </space>
        <space_list>
          <ThemeSpaceListGeneric
            list="#1d1d1d"
            list_title="#ffffff"
            list_text="#b8b8b8"
            list_text_hi="#ffaf23"
            >
          </ThemeSpaceListGeneric>
        </space_list>
      </ThemeDopeSheet>
    </dopesheet_editor>
    <image_editor>
      <ThemeImageEditor
        grid="#222222ff"
        vertex="#000000"
        vertex_select="#ff8500"
        vertex_size="3"
        vertex_bevel="#000000"
        vertex_unreferenced="#000000"
        face="#ffffff0a"
        face_select="#ff85003c"
        face_mode_select="#00000000"
        face_dot="#ff8500"
        facedot_size="3"
        freestyle_face_mark="#7fff7f33"
        face_retopology="#00000000"
        face_back="#00000000"
        face_front="#00000000"
        editmesh_active="#ffffff40"
        wire_edit="#c0c0c0"
        edge_width="1"
        edge_select="#ff8500"
        scope_back="#727272ff"
        preview_stitch_face="#7f7f0033"
        preview_stitch_edge="#ff00ff33"
        preview_stitch_vert="#0000ff33"
        preview_stitch_stitchable="#00ff00ff"
        preview_stitch_unstitchable="#ff0000ff"
        preview_stitch_active="#e1d2c323"
        uv_shadow="#707070ff"
        frame_current="#4772b3"
        metadatabg="#000000"
        metadatatext="#ffffff"
        handle_free="#000000"
        handle_auto="#909000"
        handle_align="#803060"
        handle_sel_free="#000000"
        handle_sel_auto="#f0ff40"
        handle_sel_align="#f090a0"
        handle_auto_clamped="#000000"
        handle_sel_auto_clamped="#000000"
        handle_vertex="#000000"
        handle_vertex_select="#ffff00"
        handle_vertex_size="5"
        paint_curve_handle="#7fff7f7f"
        paint_curve_pivot="#ff7f7f7f"
        >
        <space>
          <ThemeSpaceGeneric
            back="#151515"
            title="#eeeeee"
            text="#e6e6e6"
            text_hi="#ffffff"
            header="#181818ff"
            header_text="#eeeeee"
            header_text_hi="#ffffff"
            button="#15151500"
            button_title="#ffffff"
            button_text="#cccccc"
            button_text_hi="#ffffff"
            navigation_bar="#151515ff"
            execution_buts="#151515ff"
            tab_active="#151515"
            tab_inactive="#090909"
            tab_back="#090909ff"
            tab_outline="#10101000"
            >
            <panelcolors>
              <ThemePanelColors
                header="#181818ff"
                back="#181818ff"
                sub_back="#00000000"
                >
              </ThemePanelColors>
            </panelcolors>
          </ThemeSpaceGeneric>
        </space>
        <asset_shelf>
          <ThemeAssetShelf
            header_back="#181818ff"
            back="#151515ff"
            >
          </ThemeAssetShelf>
        </asset_shelf>
      </ThemeImageEditor>
    </image_editor>
    <sequence_editor>
      <ThemeSequenceEditor
        grid="#555555"
        window_sliders="#a0a0a0"
        movie_strip="#1c538c"
        movieclip_strip="#8f6e56"
        image_strip="#802d77"
        scene_strip="#888888"
        audio_strip="#0a6630"
        effect_strip="#774680"
        transition_strip="#6a5fac"
        color_strip="#8c8223"
        meta_strip="#234006"
        mask_strip="#8f5656"
        text_strip="#9f926f"
        active_strip="#eeeeee"
        selected_strip="#e65d22"
        frame_current="#38738c"
        time_scrub_background="#121212ff"
        time_marker_line="#ffffff4d"
        time_marker_line_selected="#ffffffb3"
        keyframe="#bfbfbf"
        keyframe_selected="#ffbe33"
        keyframe_breakdown="#b3dbe8"
        keyframe_breakdown_selected="#54bfed"
        keyframe_movehold="#808080"
        keyframe_movehold_selected="#ffaf23"
        keyframe_generated="#585858"
        keyframe_generated_selected="#a28962"
        keyframe_border="#000000ff"
        keyframe_border_selected="#000000ff"
        draw_action="#50c8ff"
        preview_back="#000000"
        metadatabg="#000000"
        metadatatext="#ffffff"
        preview_range="#a14d0066"
        row_alternate="#ffffff05"
        >
        <space>
          <ThemeSpaceGeneric
            back="#151515"
            title="#eeeeee"
            text="#a6a6a6"
            text_hi="#ffffff"
            header="#181818ff"
            header_text="#eeeeee"
            header_text_hi="#ffffff"
            button="#151515ff"
            button_title="#ffffff"
            button_text="#cccccc"
            button_text_hi="#ffffff"
            navigation_bar="#151515ff"
            execution_buts="#151515ff"
            tab_active="#151515"
            tab_inactive="#090909"
            tab_back="#090909ff"
            tab_outline="#10101000"
            >
            <panelcolors>
              <ThemePanelColors
                header="#181818ff"
                back="#181818ff"
                sub_back="#00000000"
                >
              </ThemePanelColors>
            </panelcolors>
          </ThemeSpaceGeneric>
        </space>
        <space_list>
          <ThemeSpaceListGeneric
            list="#181818"
            list_title="#ffffff"
            list_text="#ffffff"
            list_text_hi="#ffffff"
            >
          </ThemeSpaceListGeneric>
        </space_list>
      </ThemeSequenceEditor>
    </sequence_editor>
    <properties>
      <ThemeProperties
        match="#244959"
        active_modifier="#38738cff"
        >
        <space>
          <ThemeSpaceGeneric
            back="#151515"
            title="#e6e6e6"
            text="#e6e6e6"
            text_hi="#ffffff"
            header="#181818ff"
            header_text="#eeeeee"
            header_text_hi="#ffffff"
            button="#15151500"
            button_title="#cccccc"
            button_text="#cccccc"
            button_text_hi="#ffffff"
            navigation_bar="#090909ff"
            execution_buts="#151515ff"
            tab_active="#151515"
            tab_inactive="#090909"
            tab_back="#090909ff"
            tab_outline="#10101000"
            >
            <panelcolors>
              <ThemePanelColors
                header="#181818ff"
                back="#181818ff"
                sub_back="#00000000"
                >
              </ThemePanelColors>
            </panelcolors>
          </ThemeSpaceGeneric>
        </space>
      </ThemeProperties>
    </properties>
    <text_editor>
      <ThemeTextEditor
        line_numbers="#666666"
        line_numbers_background="#090909"
        selected_text="#606060"
        cursor="#eeeeee"
        syntax_builtin="#e61757"
        syntax_symbols="#ff5f33"
        syntax_special="#689d06"
        syntax_preprocessor="#9061e6"
        syntax_reserved="#c4753b"
        syntax_comment="#1e5916"
        syntax_string="#d4bf4a"
        syntax_numbers="#28bac7"
        >
        <space>
          <ThemeSpaceGeneric
            back="#151515"
            title="#eeeeee"
            text="#e6e6e6"
            text_hi="#ffffff"
            header="#181818ff"
            header_text="#eeeeee"
            header_text_hi="#ffffff"
            button="#15151500"
            button_title="#ffffff"
            button_text="#cccccc"
            button_text_hi="#ffffff"
            navigation_bar="#151515ff"
            execution_buts="#151515ff"
            tab_active="#151515"
            tab_inactive="#090909"
            tab_back="#090909ff"
            tab_outline="#10101000"
            >
            <panelcolors>
              <ThemePanelColors
                header="#181818ff"
                back="#181818ff"
                sub_back="#00000000"
                >
              </ThemePanelColors>
            </panelcolors>
          </ThemeSpaceGeneric>
        </space>
      </ThemeTextEditor>
    </text_editor>
    <node_editor>
      <ThemeNodeEditor
        grid="#555555"
        node_selected="#a64319"
        node_active="#ffffff"
        wire="#1a1a1aff"
        wire_inner="#8d8d8d"
        wire_select="#ffffffb3"
        selected_text="#7f7f7f"
        node_backdrop="#181818ff"
        converter_node="#0880bf"
        color_node="#e6ac00"
        group_node="#358c00"
        group_socket_node="#000000"
        frame_node="#0f0f0fcc"
        matte_node="#802b2b"
        distor_node="#287373"
        noodle_curving="5"
        grid_levels="3"
        dash_alpha="0.5"
        input_node="#d92158"
        output_node="#730b2a"
        filter_node="#551a80"
        vector_node="#3838df"
        texture_node="#bf560a"
        shader_node="#12b312"
        script_node="#0d5959"
        pattern_node="#6c696f"
        layout_node="#6c696f"
        geometry_node="#00a67e"
        attribute_node="#142566"
        simulation_zone="#592d5433"
        repeat_zone="#76512f33"
        >
        <space>
          <ThemeSpaceGeneric
            back="#151515"
            title="#eeeeee"
            text="#e6e6e6"
            text_hi="#ffffff"
            header="#181818ff"
            header_text="#eeeeee"
            header_text_hi="#ffffff"
            button="#151515ff"
            button_title="#ffffff"
            button_text="#cccccc"
            button_text_hi="#ffffff"
            navigation_bar="#151515ff"
            execution_buts="#151515ff"
            tab_active="#151515"
            tab_inactive="#090909"
            tab_back="#090909ff"
            tab_outline="#10101000"
            >
            <panelcolors>
              <ThemePanelColors
                header="#181818ff"
                back="#181818ff"
                sub_back="#00000000"
                >
              </ThemePanelColors>
            </panelcolors>
          </ThemeSpaceGeneric>
        </space>
        <space_list>
          <ThemeSpaceListGeneric
            list="#303030"
            list_title="#ffffff"
            list_text="#b8b8b8"
            list_text_hi="#ffaf23"
            >
          </ThemeSpaceListGeneric>
        </space_list>
      </ThemeNodeEditor>
    </node_editor>
    <outliner>
      <ThemeOutliner
        match="#337f33"
        selected_highlight="#153645"
        active="#244959"
        selected_object="#e96a00"
        active_object="#ffaf29"
        edited_object="#00806266"
        row_alternate="#ffffff04"
        >
        <space>
          <ThemeSpaceGeneric
            back="#151515"
            title="#ffffff"
            text="#c3c3c3"
            text_hi="#ffffff"
            header="#181818ff"
            header_text="#eeeeee"
            header_text_hi="#ffffff"
            button="#15151500"
            button_title="#ffffff"
            button_text="#cccccc"
            button_text_hi="#ffffff"
            navigation_bar="#151515ff"
            execution_buts="#151515ff"
            tab_active="#151515"
            tab_inactive="#090909"
            tab_back="#090909ff"
            tab_outline="#10101000"
            >
            <panelcolors>
              <ThemePanelColors
                header="#181818ff"
                back="#181818ff"
                sub_back="#00000000"
                >
              </ThemePanelColors>
            </panelcolors>
          </ThemeSpaceGeneric>
        </space>
      </ThemeOutliner>
    </outliner>
    <info>
      <ThemeInfo
        info_selected="#38738c"
        info_selected_text="#ffffff"
        info_error="#bf3939ff"
        info_error_text="#ffffff"
        info_warning="#ac8737ff"
        info_warning_text="#ffffff"
        info_info="#1f3862ff"
        info_info_text="#ffffff"
        info_debug="#6b3293ff"
        info_debug_text="#ffffff"
        info_property="#236666ff"
        info_property_text="#ffffff"
        info_operator="#235266ff"
        info_operator_text="#ffffff"
        >
        <space>
          <ThemeSpaceGeneric
            back="#151515"
            title="#ffffff"
            text="#c3c3c3"
            text_hi="#ffffff"
            header="#181818ff"
            header_text="#eeeeee"
            header_text_hi="#ffffff"
            button="#15151500"
            button_title="#ffffff"
            button_text="#cccccc"
            button_text_hi="#ffffff"
            navigation_bar="#151515ff"
            execution_buts="#151515ff"
            tab_active="#151515"
            tab_inactive="#090909"
            tab_back="#090909ff"
            tab_outline="#10101000"
            >
            <panelcolors>
              <ThemePanelColors
                header="#181818ff"
                back="#181818ff"
                sub_back="#00000000"
                >
              </ThemePanelColors>
            </panelcolors>
          </ThemeSpaceGeneric>
        </space>
      </ThemeInfo>
    </info>
    <preferences>
      <ThemePreferences>
        <space>
          <ThemeSpaceGeneric
            back="#151515"
            title="#eeeeee"
            text="#e6e6e6"
            text_hi="#ffffff"
            header="#181818ff"
            header_text="#eeeeee"
            header_text_hi="#ffffff"
            button="#1d1d1dff"
            button_title="#ffffff"
            button_text="#cccccc"
            button_text_hi="#ffffff"
            navigation_bar="#151515ff"
            execution_buts="#151515ff"
            tab_active="#151515"
            tab_inactive="#090909"
            tab_back="#090909ff"
            tab_outline="#10101000"
            >
            <panelcolors>
              <ThemePanelColors
                header="#181818ff"
                back="#181818ff"
                sub_back="#00000000"
                >
              </ThemePanelColors>
            </panelcolors>
          </ThemeSpaceGeneric>
        </space>
      </ThemePreferences>
    </preferences>
    <console>
      <ThemeConsole
        line_output="#71a8ff"
        line_input="#f2f2f2"
        line_info="#2e731d"
        line_error="#bf3941"
        cursor="#ffffff"
        select="#ffffff30"
        >
        <space>
          <ThemeSpaceGeneric
            back="#151515"
            title="#eeeeee"
            text="#e6e6e6"
            text_hi="#ffffff"
            header="#181818ff"
            header_text="#eeeeee"
            header_text_hi="#ffffff"
            button="#15151500"
            button_title="#ffffff"
            button_text="#cccccc"
            button_text_hi="#ffffff"
            navigation_bar="#151515ff"
            execution_buts="#151515ff"
            tab_active="#151515"
            tab_inactive="#090909"
            tab_back="#090909ff"
            tab_outline="#10101000"
            >
            <panelcolors>
              <ThemePanelColors
                header="#202020ff"
                back="#202020ff"
                sub_back="#00000000"
                >
              </ThemePanelColors>
            </panelcolors>
          </ThemeSpaceGeneric>
        </space>
      </ThemeConsole>
    </console>
    <clip_editor>
      <ThemeClipEditor
        grid="#222222ff"
        marker_outline="#000000"
        marker="#808000"
        active_marker="#ffffff"
        selected_marker="#ffff00"
        disabled_marker="#7f0000"
        locked_marker="#7f7f7f"
        path_before="#ff0000"
        path_after="#0000ff"
        path_keyframe_before="#ffc4c4"
        path_keyframe_after="#c4c4ff"
        frame_current="#4772b3"
        time_scrub_background="#181818ff"
        time_marker_line="#ffffff4d"
        time_marker_line_selected="#ffffffb3"
        strips="#ffffff"
        strips_selected="#ff8c00"
        metadatabg="#000000"
        metadatatext="#ffffff"
        handle_free="#000000"
        handle_auto="#909000"
        handle_align="#803060"
        handle_sel_free="#000000"
        handle_sel_auto="#f0ff40"
        handle_sel_align="#f090a0"
        handle_auto_clamped="#994030"
        handle_sel_auto_clamped="#f0af90"
        handle_vertex="#000000"
        handle_vertex_select="#ff8500"
        handle_vertex_size="5"
        >
        <space>
          <ThemeSpaceGeneric
            back="#151515"
            title="#eeeeee"
            text="#a6a6a6"
            text_hi="#ffffff"
            header="#181818ff"
            header_text="#eeeeee"
            header_text_hi="#ffffff"
            button="#15151500"
            button_title="#ffffff"
            button_text="#cccccc"
            button_text_hi="#ffffff"
            navigation_bar="#151515ff"
            execution_buts="#151515ff"
            tab_active="#151515"
            tab_inactive="#090909"
            tab_back="#090909ff"
            tab_outline="#10101000"
            >
            <panelcolors>
              <ThemePanelColors
                header="#181818ff"
                back="#181818ff"
                sub_back="#00000000"
                >
              </ThemePanelColors>
            </panelcolors>
          </ThemeSpaceGeneric>
        </space>
        <space_list>
          <ThemeSpaceListGeneric
            list="#303030"
            list_title="#ffffff"
            list_text="#b8b8b8"
            list_text_hi="#ffaf23"
            >
          </ThemeSpaceListGeneric>
        </space_list>
      </ThemeClipEditor>
    </clip_editor>
    <topbar>
      <ThemeTopBar>
        <space>
          <ThemeSpaceGeneric
            back="#151515"
            title="#ffffff"
            text="#e6e6e6"
            text_hi="#ffffff"
            header="#181818ff"
            header_text="#eeeeee"
            header_text_hi="#ffffff"
            button="#15151500"
            button_title="#ffffff"
            button_text="#cccccc"
            button_text_hi="#ffffff"
            navigation_bar="#151515ff"
            execution_buts="#151515ff"
            tab_active="#151515"
            tab_inactive="#090909"
            tab_back="#090909ff"
            tab_outline="#10101000"
            >
            <panelcolors>
              <ThemePanelColors
                header="#181818ff"
                back="#181818ff"
                sub_back="#00000000"
                >
              </ThemePanelColors>
            </panelcolors>
          </ThemeSpaceGeneric>
        </space>
      </ThemeTopBar>
    </topbar>
    <statusbar>
      <ThemeStatusBar>
        <space>
          <ThemeSpaceGeneric
            back="#151515"
            title="#ffffff"
            text="#838383"
            text_hi="#ffffff"
            header="#181818ff"
            header_text="#888888"
            header_text_hi="#ffffff"
            button="#15151500"
            button_title="#000000"
            button_text="#cccccc"
            button_text_hi="#ffffff"
            navigation_bar="#151515ff"
            execution_buts="#151515ff"
            tab_active="#151515"
            tab_inactive="#090909"
            tab_back="#090909ff"
            tab_outline="#10101000"
            >
            <panelcolors>
              <ThemePanelColors
                header="#181818ff"
                back="#181818ff"
                sub_back="#00000000"
                >
              </ThemePanelColors>
            </panelcolors>
          </ThemeSpaceGeneric>
        </space>
      </ThemeStatusBar>
    </statusbar>
    <spreadsheet>
      <ThemeSpreadsheet
        row_alternate="#ffffff04"
        >
        <space>
          <ThemeSpaceGeneric
            back="#151515"
            title="#ffffff"
            text="#c3c3c3"
            text_hi="#ffffff"
            header="#181818ff"
            header_text="#eeeeee"
            header_text_hi="#ffffff"
            button="#15151500"
            button_title="#ffffff"
            button_text="#cccccc"
            button_text_hi="#ffffff"
            navigation_bar="#151515ff"
            execution_buts="#151515ff"
            tab_active="#151515"
            tab_inactive="#090909"
            tab_back="#090909ff"
            tab_outline="#10101000"
            >
            <panelcolors>
              <ThemePanelColors
                header="#181818ff"
                back="#181818ff"
                sub_back="#00000000"
                >
              </ThemePanelColors>
            </panelcolors>
          </ThemeSpaceGeneric>
        </space>
        <space_list>
          <ThemeSpaceListGeneric
            list="#303030"
            list_title="#c3c3c3"
            list_text="#b8b8b8"
            list_text_hi="#ffaf23"
            >
          </ThemeSpaceListGeneric>
        </space_list>
      </ThemeSpreadsheet>
    </spreadsheet>
    <bone_color_sets>
      <ThemeBoneColorSet
        normal="#9a0000"
        select="#bd1111"
        active="#f70a0a"
        show_colored_constraints="FALSE"
        >
      </ThemeBoneColorSet>
      <ThemeBoneColorSet
        normal="#f74018"
        select="#f66913"
        active="#fa9900"
        show_colored_constraints="FALSE"
        >
      </ThemeBoneColorSet>
      <ThemeBoneColorSet
        normal="#1e9109"
        select="#59b70b"
        active="#83ef1d"
        show_colored_constraints="FALSE"
        >
      </ThemeBoneColorSet>
      <ThemeBoneColorSet
        normal="#0a3694"
        select="#3667df"
        active="#5ec1ef"
        show_colored_constraints="FALSE"
        >
      </ThemeBoneColorSet>
      <ThemeBoneColorSet
        normal="#a9294e"
        select="#c1416a"
        active="#f05d91"
        show_colored_constraints="FALSE"
        >
      </ThemeBoneColorSet>
      <ThemeBoneColorSet
        normal="#430c78"
        select="#543aa3"
        active="#8764d5"
        show_colored_constraints="FALSE"
        >
      </ThemeBoneColorSet>
      <ThemeBoneColorSet
        normal="#24785a"
        select="#3c9579"
        active="#6fb6ab"
        show_colored_constraints="FALSE"
        >
      </ThemeBoneColorSet>
      <ThemeBoneColorSet
        normal="#4b707c"
        select="#6a8691"
        active="#9bc2cd"
        show_colored_constraints="FALSE"
        >
      </ThemeBoneColorSet>
      <ThemeBoneColorSet
        normal="#f4c90c"
        select="#eec236"
        active="#f3ff00"
        show_colored_constraints="FALSE"
        >
      </ThemeBoneColorSet>
      <ThemeBoneColorSet
        normal="#1e2024"
        select="#484c56"
        active="#ffffff"
        show_colored_constraints="FALSE"
        >
      </ThemeBoneColorSet>
      <ThemeBoneColorSet
        normal="#6f2f6a"
        select="#9845be"
        active="#d330d6"
        show_colored_constraints="FALSE"
        >
      </ThemeBoneColorSet>
      <ThemeBoneColorSet
        normal="#6c8e22"
        select="#7fb022"
        active="#bbef5b"
        show_colored_constraints="FALSE"
        >
      </ThemeBoneColorSet>
      <ThemeBoneColorSet
        normal="#8d8d8d"
        select="#b0b0b0"
        active="#dedede"
        show_colored_constraints="FALSE"
        >
      </ThemeBoneColorSet>
      <ThemeBoneColorSet
        normal="#834326"
        select="#8b5811"
        active="#bd6a11"
        show_colored_constraints="FALSE"
        >
      </ThemeBoneColorSet>
      <ThemeBoneColorSet
        normal="#08310e"
        select="#1c430b"
        active="#34622b"
        show_colored_constraints="FALSE"
        >
      </ThemeBoneColorSet>
      <ThemeBoneColorSet
        normal="#000000"
        select="#000000"
        active="#000000"
        show_colored_constraints="FALSE"
        >
      </ThemeBoneColorSet>
      <ThemeBoneColorSet
        normal="#000000"
        select="#000000"
        active="#000000"
        show_colored_constraints="FALSE"
        >
      </ThemeBoneColorSet>
      <ThemeBoneColorSet
        normal="#000000"
        select="#000000"
        active="#000000"
        show_colored_constraints="FALSE"
        >
      </ThemeBoneColorSet>
      <ThemeBoneColorSet
        normal="#000000"
        select="#000000"
        active="#000000"
        show_colored_constraints="FALSE"
        >
      </ThemeBoneColorSet>
      <ThemeBoneColorSet
        normal="#000000"
        select="#000000"
        active="#000000"
        show_colored_constraints="FALSE"
        >
      </ThemeBoneColorSet>
    </bone_color_sets>
    <collection_color>
      <ThemeCollectionColor
        color="#bf3e39"
        >
      </ThemeCollectionColor>
      <ThemeCollectionColor
        color="#d9822b"
        >
      </ThemeCollectionColor>
      <ThemeCollectionColor
        color="#d9bd0b"
        >
      </ThemeCollectionColor>
      <ThemeCollectionColor
        color="#47b347"
        >
      </ThemeCollectionColor>
      <ThemeCollectionColor
        color="#2195d9"
        >
      </ThemeCollectionColor>
      <ThemeCollectionColor
        color="#6c37b9"
        >
      </ThemeCollectionColor>
      <ThemeCollectionColor
        color="#b359a3"
        >
      </ThemeCollectionColor>
      <ThemeCollectionColor
        color="#734940"
        >
      </ThemeCollectionColor>
    </collection_color>
    <strip_color>
      <ThemeStripColor
        color="#cc5a52"
        >
      </ThemeStripColor>
      <ThemeStripColor
        color="#cc8a48"
        >
      </ThemeStripColor>
      <ThemeStripColor
        color="#b3a33f"
        >
      </ThemeStripColor>
      <ThemeStripColor
        color="#5c995c"
        >
      </ThemeStripColor>
      <ThemeStripColor
        color="#519fcc"
        >
      </ThemeStripColor>
      <ThemeStripColor
        color="#8d59da"
        >
      </ThemeStripColor>
      <ThemeStripColor
        color="#c673b8"
        >
      </ThemeStripColor>
      <ThemeStripColor
        color="#996952"
        >
      </ThemeStripColor>
      <ThemeStripColor
        color="#808080"
        >
      </ThemeStripColor>
    </strip_color>
  </Theme>
  <ThemeStyle>
    <panel_title>
      <ThemeFontStyle
        points="11"
        character_weight="400"
        shadow="0"
        shadow_offset_x="0"
        shadow_offset_y="-1"
        shadow_alpha="0"
        shadow_value="0"
        >
      </ThemeFontStyle>
    </panel_title>
    <widget_label>
      <ThemeFontStyle
        points="11"
        character_weight="400"
        shadow="0"
        shadow_offset_x="0"
        shadow_offset_y="-1"
        shadow_alpha="0"
        shadow_value="0"
        >
      </ThemeFontStyle>
    </widget_label>
    <widget>
      <ThemeFontStyle
        points="11"
        character_weight="400"
        shadow="0"
        shadow_offset_x="0"
        shadow_offset_y="-1"
        shadow_alpha="0"
        shadow_value="0"
        >
      </ThemeFontStyle>
    </widget>
  </ThemeStyle>
</bpy>
